{
	"format_version": "1.9.0",
	"credit": "Made with Blockbench",
	"parent": "block/block",
	"texture_size": [32, 32],
	"textures": {
		"all": "create_fantasizing:block/sculk_engine",
		"particle": "block/sculk"
	},
	"elements": [
		{
			"name": "Back",
			"from": [2.5, 2.5, 0],
			"to": [13.5, 13.5, 2],
			"faces": {
				"north": {"uv": [5, 5, 10.5, 10.5], "texture": "#all", "cullface": "north"},
				"east": {"uv": [7.5, 10.5, 6.5, 16], "texture": "#all"},
				"south": {"uv": [10.5, 5, 16, 10.5], "texture": "#all"},
				"west": {"uv": [6.5, 10.5, 7.5, 16], "texture": "#all"},
				"up": {"uv": [6.5, 10.5, 7.5, 16], "rotation": 90, "texture": "#all"},
				"down": {"uv": [6.5, 10.5, 7.5, 16], "rotation": 270, "texture": "#all"}
			}
		},
		{
			"name": "Front",
			"from": [3, 3, 7],
			"to": [13, 13, 14],
			"faces": {
				"north": {"uv": [13.5, 0, 8.5, 5], "texture": "#all"},
				"east": {"uv": [5, 0, 8.5, 5], "texture": "#all"},
				"south": {"uv": [5, 0, 0, 5], "texture": "#all"},
				"west": {"uv": [8.5, 0, 5, 5], "texture": "#all"},
				"up": {"uv": [8.5, 0, 5, 5], "rotation": 90, "texture": "#all"},
				"down": {"uv": [0, 8.5, 5, 5], "texture": "#all"}
			}
		},
		{
			"name": "Base",
			"from": [3, 0, 1],
			"to": [13, 3, 13],
			"faces": {
				"north": {"uv": [1, 14.5, 6, 16], "texture": "#all"},
				"east": {"uv": [0.5, 14.5, 6.5, 16], "texture": "#all"},
				"south": {"uv": [0.5, 14.5, 5.5, 16], "texture": "#all"},
				"west": {"uv": [0, 14.5, 6, 16], "texture": "#all"},
				"up": {"uv": [0, 8.5, 5, 14.5], "texture": "#all"},
				"down": {"uv": [0, 8.5, 5, 14.5], "texture": "#all", "cullface": "down"}
			}
		},
		{
			"name": "Panel",
			"from": [3, 5, 4],
			"to": [4, 11, 7],
			"faces": {
				"north": {"uv": [14.5, 1, 15, 4], "texture": "#all"},
				"east": {"uv": [13.5, 1, 15, 4], "texture": "#all"},
				"west": {"uv": [13.5, 1, 15, 4], "rotation": 180, "texture": "#all"},
				"up": {"uv": [13.5, 1, 15, 1.5], "rotation": 270, "texture": "#all"},
				"down": {"uv": [13.5, 3.5, 15, 4], "rotation": 90, "texture": "#all"}
			}
		},
		{
			"name": "Panel",
			"from": [5, 12, 4],
			"to": [11, 13, 7],
			"faces": {
				"north": {"uv": [14.5, 1, 15, 4], "rotation": 270, "texture": "#all"},
				"east": {"uv": [13.5, 1, 15, 1.5], "texture": "#all"},
				"west": {"uv": [13.5, 3.5, 15, 4], "rotation": 180, "texture": "#all"},
				"up": {"uv": [13.5, 1, 15, 4], "rotation": 270, "texture": "#all"},
				"down": {"uv": [13.5, 1, 15, 4], "rotation": 90, "texture": "#all"}
			}
		},
		{
			"name": "Panel",
			"from": [12, 5, 4],
			"to": [13, 11, 7],
			"faces": {
				"north": {"uv": [14.5, 1, 15, 4], "texture": "#all"},
				"east": {"uv": [13.5, 1, 15, 4], "texture": "#all"},
				"west": {"uv": [13.5, 1, 15, 4], "rotation": 180, "texture": "#all"},
				"up": {"uv": [13.5, 1, 15, 1.5], "rotation": 270, "texture": "#all"},
				"down": {"uv": [13.5, 3.5, 15, 4], "rotation": 90, "texture": "#all"}
			}
		},
		{
			"name": "Frame",
			"from": [2.5, 11.5, 2],
			"to": [4.5, 13.5, 10],
			"faces": {
				"east": {"uv": [15, 0, 16, 4], "rotation": 270, "texture": "#all"},
				"south": {"uv": [14, 0, 15, 1], "texture": "#all"},
				"west": {"uv": [15, 0, 16, 4], "rotation": 90, "texture": "#all"},
				"up": {"uv": [16, 0, 15, 4], "rotation": 180, "texture": "#all"},
				"down": {"uv": [16, 0, 15, 4], "texture": "#all"}
			}
		},
		{
			"name": "Frame",
			"from": [11.5, 11.5, 2],
			"to": [13.5, 13.5, 10],
			"faces": {
				"east": {"uv": [16, 0, 15, 4], "rotation": 270, "texture": "#all"},
				"south": {"uv": [14, 0, 15, 1], "rotation": 90, "texture": "#all"},
				"west": {"uv": [16, 0, 15, 4], "rotation": 90, "texture": "#all"},
				"up": {"uv": [15, 0, 16, 4], "rotation": 180, "texture": "#all"},
				"down": {"uv": [15, 0, 16, 4], "texture": "#all"}
			}
		},
		{
			"name": "Frame",
			"from": [11.5, 2.5, 2],
			"to": [13.5, 4.5, 10],
			"faces": {
				"east": {"uv": [15, 0, 16, 4], "rotation": 270, "texture": "#all"},
				"south": {"uv": [14, 0, 15, 1], "rotation": 180, "texture": "#all"},
				"west": {"uv": [15, 0, 16, 4], "rotation": 90, "texture": "#all"},
				"up": {"uv": [16, 0, 15, 4], "rotation": 180, "texture": "#all"},
				"down": {"uv": [16, 0, 15, 4], "texture": "#all"}
			}
		},
		{
			"name": "Frame",
			"from": [2.5, 2.5, 2],
			"to": [4.5, 4.5, 10],
			"faces": {
				"east": {"uv": [16, 0, 15, 4], "rotation": 270, "texture": "#all"},
				"south": {"uv": [14, 0, 15, 1], "rotation": 270, "texture": "#all"},
				"west": {"uv": [16, 0, 15, 4], "rotation": 90, "texture": "#all"},
				"up": {"uv": [15, 0, 16, 4], "rotation": 180, "texture": "#all"},
				"down": {"uv": [15, 0, 16, 4], "texture": "#all"}
			}
		},
		{
			"name": "Ear",
			"from": [2.5, 6.5, 2],
			"to": [3.5, 9.5, 5],
			"faces": {
				"east": {"uv": [12.5, 7, 14, 8.5], "rotation": 270, "texture": "#all"},
				"south": {"uv": [9, 10.5, 9.5, 12], "texture": "#all"},
				"west": {"uv": [7.5, 10.5, 9, 12], "texture": "#all"},
				"up": {"uv": [9, 10.5, 9.5, 12], "texture": "#all"},
				"down": {"uv": [9, 10.5, 9.5, 12], "texture": "#all"}
			}
		},
		{
			"name": "Ear",
			"from": [12.5, 6.5, 2],
			"to": [13.5, 9.5, 5],
			"faces": {
				"east": {"uv": [7.5, 10.5, 9, 12], "rotation": 180, "texture": "#all"},
				"south": {"uv": [9, 10.5, 9.5, 12], "texture": "#all"},
				"west": {"uv": [12.5, 7, 14, 8.5], "texture": "#all"},
				"up": {"uv": [9, 10.5, 9.5, 12], "texture": "#all"},
				"down": {"uv": [9, 10.5, 9.5, 12], "texture": "#all"}
			}
		},
		{
			"name": "Ear",
			"from": [6.5, 12.5, 2],
			"to": [9.5, 13.5, 5],
			"faces": {
				"east": {"uv": [9, 10.5, 9.5, 12], "rotation": 90, "texture": "#all"},
				"south": {"uv": [9, 10.5, 9.5, 12], "rotation": 90, "texture": "#all"},
				"west": {"uv": [9, 10.5, 9.5, 12], "rotation": 90, "texture": "#all"},
				"up": {"uv": [7.5, 10.5, 9, 12], "rotation": 90, "texture": "#all"},
				"down": {"uv": [12.5, 7, 14, 8.5], "rotation": 270, "texture": "#all"}
			}
		},
		{
			"name": "Ear",
			"from": [6.5, 2.5, 2],
			"to": [9.5, 3.5, 5],
			"faces": {
				"east": {"uv": [9, 10.5, 9.5, 12], "rotation": 90, "texture": "#all"},
				"south": {"uv": [9, 10.5, 9.5, 12], "rotation": 90, "texture": "#all"},
				"west": {"uv": [9, 10.5, 9.5, 12], "rotation": 90, "texture": "#all"},
				"up": {"uv": [12.5, 7, 14, 8.5], "rotation": 90, "texture": "#all"}
			}
		}
	],
	"display": {
		"gui": {
			"rotation": [30, 45, 0],
			"scale": [0.625, 0.625, 0.625]
		}
	}
}